{
  "timestamp": "2025-12-10T09:20:36.889400Z",
  "event_type": "phone_detected",
  "frame_idx": null,
  "image_path": "D:\\yolo_detection_member3\\src\\..\\evidence\\phone_detected_20251210_145036_264be9.jpg",
  "detections": [
    {
      "class": "person",
      "confidence": 0.9071044325828552,
      "box": [
        17.0,
        65.0,
        612.0,
        478.0
      ]
    },
    {
      "class": "cell phone",
      "confidence": 0.6690200567245483,
      "box": [
        69.0,
        79.0,
        305.0,
        477.0
      ]
    }
  ],
  "extra": {}
}